{
    "De Volkskrant": {
        "last_article_url": "https:\/\/www.volkskrant.nl\/columns-van-de-dag\/hoopgevende-verandering-komt-van-mensen-die-zelf-na-politieke-keuzen-de-consequenties-voelen~bed1556e8\/",
        "last_scraped_at": "2025-07-12 12:30:27",
        "articles_found": 10
    },
    "NRC": {
        "last_article_url": "https:\/\/www.nrc.nl\/nieuws\/2025\/07\/12\/de-haagse-zaken-zomer-qa-a4900107",
        "last_scraped_at": "2025-07-12 12:30:27",
        "articles_found": 10
    },
    "Trouw": {
        "last_article_url": "https:\/\/www.trouw.nl\/politiek\/vinden-sgp-ers-zelf-nog-dat-ze-het-staatsrechtelijk-geweten-zijn~b01a807b\/",
        "last_scraped_at": "2025-07-12 12:30:28",
        "articles_found": 3
    },
    "Telegraaf": {
        "last_article_url": "https:\/\/www.telegraaf.nl\/sport\/wielrennen\/live-tour-de-france-vluchters-gezocht-achtste-etappe-lijkt-sprintersbal-te-worden\/77432260.html",
        "last_scraped_at": "2025-07-12 12:30:28",
        "articles_found": 10
    },
    "AD": {
        "last_article_url": "https:\/\/www.ad.nl\/politiek\/critici-van-yesilgoz-houden-zich-stil-maar-ze-zijn-er-wel-in-appgroep-tellen-leden-30-fouten~a6304083\/",
        "last_scraped_at": "2025-07-12 12:30:28",
        "articles_found": 10
    },
    "NU.nl": {
        "last_article_url": "https:\/\/www.nu.nl\/klimaat\/6362165\/twijfels-over-klimaatambities-eu-lidstaten-en-parlement-trappen-op-de-rem.html",
        "last_scraped_at": "2025-07-12 12:30:28",
        "articles_found": 10
    }
}